LICENCE
asuscharged/__init__.py
asuscharged/__main__.py
asuscharged/config.py
asuscharged/notify.py
data/asuscharged.service
data/ca.cforrester.AsusChargeDaemon1.conf
data/ca.cforrester.AsusChargeDaemon1.service
data/ca.cforrester.AsusChargeDaemon1.xml
install.py
asus_charge_daemon-0.3.2.dist-info/entry_points.txt
asus_charge_daemon-0.3.2.dist-info/WHEEL
asus_charge_daemon-0.3.2.dist-info/METADATA
asus_charge_daemon-0.3.2.dist-info/RECORD
