Metadata-Version: 2.1
Name: asus-charge-daemon
Version: 0.3.2
Summary: A daemon exposing D-Bus services for managing the charge level of recent ASUS notebooks.
Home-page: https://github.com./cforrester1988/asus-charge-daemon
License: GPL-3.0-or-later
Author: Christopher Forrester
Author-email: christopher@cforrester.ca
Requires-Python: >=3.7,<4.0
Classifier: Development Status :: 4 - Beta
Classifier: Environment :: No Input/Output (Daemon)
Classifier: Intended Audience :: End Users/Desktop
Classifier: License :: OSI Approved :: GNU General Public License v3 or later (GPLv3+)
Classifier: Operating System :: POSIX :: Linux
Classifier: Programming Language :: Python :: 3
Classifier: Programming Language :: Python :: 3.7
Classifier: Programming Language :: Python :: 3.8
Classifier: Programming Language :: Python :: 3.9
Classifier: Topic :: System
Requires-Dist: PyGObject (>=3.38.0,<4.0.0)
Requires-Dist: asus-charge-control (>=1.0.3,<2.0.0)
Requires-Dist: asyncinotify (>=2.0.2,<3.0.0)
Requires-Dist: dbus-next (>=0.2.2,<0.3.0)
